libICEpost/GLOBALS.py
libICEpost/__init__.py
libICEpost/Database/_DatabaseClass.py
libICEpost/Database/__init__.py
libICEpost/Database/chemistry/__init__.py
libICEpost/Database/chemistry/constants.py
libICEpost/Database/chemistry/reactions/StoichiometricReaction.py
libICEpost/Database/chemistry/reactions/__init__.py
libICEpost/Database/chemistry/specie/Mixtures.py
libICEpost/Database/chemistry/specie/Molecules.py
libICEpost/Database/chemistry/specie/__init__.py
libICEpost/Database/chemistry/specie/periodicTable.py
libICEpost/Database/chemistry/thermo/__init__.py
libICEpost/Database/chemistry/thermo/EquationOfState/__init__.py
libICEpost/Database/chemistry/thermo/Thermo/__init__.py
libICEpost/Database/chemistry/thermo/Thermo/constantCp.py
libICEpost/Database/chemistry/thermo/Thermo/janaf7.py
libICEpost/Database/data/Fuels.json
libICEpost/Database/data/Mixtures.json
libICEpost/Database/data/Molecules.json
libICEpost/Database/data/Oxidizers.json
libICEpost/Database/data/StoichiometricReaction.json
libICEpost/Database/data/constantCp.json
libICEpost/Database/data/janaf7.json
libICEpost/scripts/__init__.py
libICEpost/scripts/applyPatches.py
libICEpost/src/__init__.py
libICEpost/src/_utils/__init__.py
libICEpost/src/_utils/PyFoam/Error.py
libICEpost/src/_utils/PyFoam/FoamInformation.py
libICEpost/src/_utils/PyFoam/__init__.py
libICEpost/src/_utils/PyFoam/Applications/APoMaFoXiiQt.py
libICEpost/src/_utils/PyFoam/Applications/AddCaseDataToDatabase.py
libICEpost/src/_utils/PyFoam/Applications/Benchmark.py
libICEpost/src/_utils/PyFoam/Applications/BinarySize.py
libICEpost/src/_utils/PyFoam/Applications/BlockMeshConverter.py
libICEpost/src/_utils/PyFoam/Applications/BlockMeshRewrite.py
libICEpost/src/_utils/PyFoam/Applications/BuildHelper.py
libICEpost/src/_utils/PyFoam/Applications/CaseBuilder.py
libICEpost/src/_utils/PyFoam/Applications/CaseBuilderBackend.py
libICEpost/src/_utils/PyFoam/Applications/CaseReport.py
libicepost-0.10.3.dist-info/licenses/LICENSE
libicepost-0.10.3.dist-info/METADATA
libicepost-0.10.3.dist-info/WHEEL
libicepost-0.10.3.dist-info/top_level.txt
libicepost-0.10.3.dist-info/RECORD
