Metadata-Version: 2.4
Name: libICEpost
Version: 0.10.3
Summary: Postprocessing of data sampled from internal combustion engines (Experimental, 1D/0D (Gasdyn), 3D (LibICE), etc.)
Author-email: Federico Ramognino <federico.ramognino@polimi.it>
License-Expression: MIT
Project-URL: Homepage, https://github.com/RamogninoF/LibICE-post
Project-URL: Issues, https://github.com/RamogninoF/LibICE-post/issues
Classifier: Development Status :: 3 - Alpha
Classifier: Programming Language :: Python :: 3
Classifier: Programming Language :: Python :: 3.11
Classifier: Operating System :: OS Independent
Requires-Python: ~=3.11
License-File: LICENSE
Requires-Dist: chempy
Requires-Dist: tqdm
Requires-Dist: colorama
Requires-Dist: pandas
Requires-Dist: bidict
Requires-Dist: cantera
Requires-Dist: numpy
Requires-Dist: cachetools
Requires-Dist: foamlib>=1.3.5
Dynamic: license-file
